{
  "Vip": [
    {
      "id": "638814970204913695",
      "nome": "Taty 👘",
      "vip": "ouro",
      "dia": 5,
      "mes": 5
    },
    {
      "id": "469690112695861280",
      "nome": "Jackson55",
      "vip": "ouro",
      "dia": 5,
      "mes": 5
    },
    {
      "id": "385617617886511114",
      "nome": "Mattias",
      "vip": "vip",
      "dia": 5,
      "mes": 5
    },
    {
      "id": "700163173667569784",
      "nome": "zhueca",
      "vip": "vip",
      "dia": 4,
      "mes": 5
    },
    {
      "id": "389181278408146964",
      "nome": "Yasmin",
      "vip": "vip",
      "dia": 1,
      "mes": 5
    },
    {
      "id": "577692260355932160",
      "nome": "ITQUES",
      "vip": "prata",
      "dia": 4,
      "mes": 5
    },
    {
      "id": "533753395555729438",
      "nome": "Hikune",
      "vip": "vip",
      "dia": 9,
      "mes": 5
    },
    {
      "id": "392434224105521184",
      "nome": "sky0ver",
      "vip": "prata",
      "dia": 9,
      "mes": 5
    },
    {
      "id": "576444758390472704",
      "nome": "Maraysa",
      "vip": "ouro",
      "dia": 9,
      "mes": 5
    }
  ]
}